odoo/addons/sale_timesheet_brand/README.rst
odoo/addons/sale_timesheet_brand/__init__.py
odoo/addons/sale_timesheet_brand/__manifest__.py
odoo/addons/sale_timesheet_brand/i18n/sale_timesheet_brand.pot
odoo/addons/sale_timesheet_brand/models/__init__.py
odoo/addons/sale_timesheet_brand/models/sale_order_line.py
odoo/addons/sale_timesheet_brand/readme/CONTRIBUTORS.rst
odoo/addons/sale_timesheet_brand/readme/DESCRIPTION.rst
odoo/addons/sale_timesheet_brand/readme/USAGE.rst
odoo/addons/sale_timesheet_brand/static/description/icon.png
odoo/addons/sale_timesheet_brand/static/description/index.html
odoo/addons/sale_timesheet_brand/tests/__init__.py
odoo/addons/sale_timesheet_brand/tests/test_sale_timesheet_brand.py
odoo13_addon_sale_timesheet_brand-13.0.1.0.1.dev3.dist-info/METADATA
odoo13_addon_sale_timesheet_brand-13.0.1.0.1.dev3.dist-info/WHEEL
odoo13_addon_sale_timesheet_brand-13.0.1.0.1.dev3.dist-info/top_level.txt
odoo13_addon_sale_timesheet_brand-13.0.1.0.1.dev3.dist-info/RECORD
